{
  "components": [
    {
      "name": "Accordion",
      "path": "/components/accordion",
      "routes": [
        { "name": "Базовый пример", "path": "/components/accordion" },
        { "name": "Размеры", "path": "/components/accordion/accordionDimension" },
        { "name": "Скрытие разделителей", "path": "/components/accordion/accordionDivider" },
        { "name": "Расположение шеврона слева", "path": "/components/accordion/accordionIcon" },
        { "name": "Режимы использования", "path": "/components/accordion/accordionModes" }
      ]
    },
    {
      "name": "ActionBar",
      "path": "/components/actionBar",
      "routes": [
        { "name": "Базовый пример", "path": "/components/actionBar" },
        { "name": "Размеры", "path": "/components/actionBar/dimensions" },
        { "name": "Адаптив. Overflow Menu", "path": "/components/actionBar/adaptive" }
      ]
    },
    {
      "name": "Avatar",
      "path": "/components/avatar",
      "routes": [
        { "name": "Базовый пример", "path": "/components/avatar" },
        { "name": "Стили", "path": "/components/avatar/styles" },
        { "name": "Размер XXS", "path": "/components/avatar/sizeXXS" },
        { "name": "Группировка", "path": "/components/avatar/avatarGroup" },
        { "name": "Группировка при ограниченной ширине", "path": "/components/avatar/avatarGroupLimitedWidth" }
      ]
    },
    {
      "name": "Breadcrumbs",
      "path": "/components/breadcrumbs",
      "routes": [
        { "name": "Базовый пример", "path": "/components/breadcrumbs" },
        { "name": "Размеры", "path": "/components/breadcrumbs/sizes" },
        { "name": "Пример вкладок с иконками", "path": "/components/breadcrumbs/icons" },
        { "name": "Mobile", "path": "/components/breadcrumbs/mobile" },
        { "name": "Пример с активной/неактивной последней вкладкой", "path": "/components/breadcrumbs/activeCrumb" },
        { "name": "Пример с react-router", "path": "/components/breadcrumbs/link" }
      ]
    },
    {
      "name": "Link",
      "path": "/components/link",
      "routes": [
        { "name": "Базовый пример", "path": "/components/link" },
        { "name": "Стили", "path": "/components/link/styles" },
        { "name": "С иконками", "path": "/components/link/withIcon" },
        { "name": "Css Mixin", "path": "/components/link/cssMixin" },
        { "name": "Link As Prop", "path": "/components/link/asProp" }
      ]
    },
    {
      "name": "Button",
      "path": "/components/button",
      "routes": [
        { "name": "Базовый пример", "path": "/components/button" },
        { "name": "Размеры", "path": "/components/button/dimension" },
        { "name": "Типы", "path": "/components/button/types" },
        { "name": "Состояния", "path": "/components/button/state" },
        { "name": "С иконкой", "path": "/components/button/buttonWithIcon" },
        { "name": "С бейджем", "path": "/components/button/buttonWithBadge" },
        { "name": "Адаптив", "path": "/components/button/adaptive" }
      ]
    },
    {
      "name": "ButtonGroup",
      "path": "/components/buttonGroup",
      "routes": [
        { "name": "Базовый пример", "path": "/components/buttonGroup" },
        { "name": "Стили", "path": "/components/buttonGroup/styles" },
        { "name": "Размеры", "path": "/components/buttonGroup/sizes" },
        { "name": "Состояния", "path": "/components/buttonGroup/states" },
        { "name": "Варианты", "path": "/components/buttonGroup/variants" }
      ]
    },
    {
      "name": "IconButton",
      "path": "/components/iconButton",
      "routes": [
        { "name": "Базовый пример", "path": "/components/iconButton" },
        { "name": "Стили", "path": "/components/iconButton/styles" },
        { "name": "Состояния", "path": "/components/iconButton/states" }
      ]
    },
    {
      "name": "IconButtonGroup",
      "path": "/components/iconButtonGroup",
      "routes": [
        { "name": "Базовый пример", "path": "/components/iconButtonGroup" },
        { "name": "Размеры", "path": "/components/iconButtonGroup/sizes" },
        { "name": "Состояния", "path": "/components/iconButtonGroup/states" },
        { "name": "Tooltip", "path": "/components/iconButtonGroup/tooltip" }
      ]
    },
    {
      "name": "IconPlacement",
      "path": "/components/iconPlacement",
      "routes": [
        { "name": "Базовый пример", "path": "/components/iconPlacement" },
        { "name": "Стили", "path": "/components/iconPlacement/styles" },
        { "name": "Размеры", "path": "/components/iconPlacement/sizes" },
        { "name": "Варианты использования", "path": "/components/iconPlacement/variants" }
      ]
    },
    {
      "name": "MenuButton",
      "path": "/components/menuButton",
      "routes": [
        { "name": "Базовый пример", "path": "/components/menuButton" },
        { "name": "Стили", "path": "/components/menuButton/styles" },
        { "name": "С иконкой", "path": "/components/menuButton/withIcon" },
        { "name": "Состояния", "path": "/components/menuButton/states" },
        {
          "name": "Задизейбленные и кастомизированные опции и панель с кнопками",
          "path": "/components/menuButton/actions"
        },
        {
          "name": "С чекбоксами и нижней панелью в выпадающем меню",
          "path": "/components/menuButton/checkboxAndBottomPanel"
        },
        {
          "name": "С чекбоксами и верхней панелью в выпадающем меню",
          "path": "/components/menuButton/checkboxAndTopPanel"
        },
        { "name": "С многоуровневым меню", "path": "/components/menuButton/multiLevelMenu" }
      ]
    },
    {
      "name": "MultiButton",
      "path": "/components/multiButton",
      "routes": [
        { "name": "Базовый пример", "path": "/components/multiButton" },
        { "name": "Стили", "path": "/components/multiButton/styles" },
        { "name": "С иконкой", "path": "/components/multiButton/withIcon" },
        { "name": "Состояния", "path": "/components/multiButton/states" }
      ]
    },
    {
      "name": "TextButton",
      "path": "/components/textButton",
      "routes": [
        { "name": "Базовый пример", "path": "/components/textButton" },
        { "name": "Размеры и стили", "path": "/components/textButton/styles" },
        { "name": "Состояния", "path": "/components/textButton/states" }
      ]
    },
    {
      "name": "TextButtonMenu",
      "path": "/components/textButtonMenu",
      "routes": [
        { "name": "Базовый пример", "path": "/components/textButtonMenu" },
        { "name": "Размеры и стили", "path": "/components/textButtonMenu/styles" },
        { "name": "Состояния", "path": "/components/textButtonMenu/states" }
      ]
    },
    {
      "name": "FloatingButton",
      "path": "/components/floatingButton",
      "routes": [
        { "name": "Базовый пример", "path": "/components/floatingButton" },
        { "name": "Размеры и стили", "path": "/components/floatingButton/styles" },
        { "name": "Пример с Tooltip", "path": "/components/floatingButton/tooltip" },
        { "name": "Расположение", "path": "/components/floatingButton/position" },
        { "name": "Mobile", "path": "/components/floatingButton/mobile" },
        { "name": "FloatingButtonMenu", "path": "/components/floatingButton/withMenu" },
        { "name": "FloatingButtonMenu. Режимы использования", "path": "/components/floatingButton/withMenuModes" }
      ]
    },
    {
      "name": "Carousel",
      "path": "/components/carousel",
      "routes": [
        { "name": "Базовый пример", "path": "/components/carousel" },
        { "name": "Позиция слайдера", "path": "/components/carousel/sliderPosition" },
        { "name": "Листание слайдов", "path": "/components/carousel/arrows" },
        { "name": "Автоматическое переключение", "path": "/components/carousel/carouselAutoChange" }
      ]
    },
    {
      "name": "CarouselSlider",
      "path": "/components/carouselSlider",
      "routes": [
        { "name": "Базовый пример", "path": "/components/carouselSlider" },
        { "name": "Стили", "path": "/components/carouselSlider/styles" },
        { "name": "Автоматическое переключение", "path": "/components/carouselSlider/carouselSliderAutoChange" }
      ]
    },
    {
      "name": "CheckboxField",
      "path": "/components/checkbox",
      "routes": [
        { "name": "Базовый пример", "path": "/components/checkbox" },
        { "name": "Состояния", "path": "/components/checkbox/states" },
        { "name": "Вариация с дополнительным текстом", "path": "/components/checkbox/additionalText" },
        { "name": "Вариация с информером", "path": "/components/checkbox/withInformer" },
        { "name": "Группа чекбоксов", "path": "/components/checkbox/fieldSet" },
        { "name": "Составная группа чекбоксов", "path": "/components/checkbox/compositeGroup" }
      ]
    },
    {
      "name": "RadioButton",
      "path": "/components/radiobutton",
      "routes": [
        { "name": "Базовый пример", "path": "/components/radiobutton" },
        { "name": "Размеры", "path": "/components/radiobutton/sizes" },
        { "name": "Состояния", "path": "/components/radiobutton/states" },
        { "name": "Дополнительный текст", "path": "/components/radiobutton/extraText" },
        { "name": "Информер", "path": "/components/radiobutton/informer" },
        { "name": "Группа", "path": "/components/radiobutton/fieldSet" }
      ]
    },
    {
      "name": "Toggle",
      "path": "/components/toggle",
      "routes": [
        { "name": "Базовый пример", "path": "/components/toggle" },
        { "name": "Размеры", "path": "/components/toggle/sizes" },
        { "name": "Состояния", "path": "/components/toggle/states" },
        { "name": "Расположение текста", "path": "/components/toggle/labelPosition" },
        { "name": "Дополнительный текст", "path": "/components/toggle/extraText" },
        { "name": "Адаптив", "path": "/components/toggle/mobile" }
      ]
    },
    {
      "name": "ContentSwitcher",
      "path": "/components/contentSwitcher",
      "routes": [
        { "name": "Базовый пример", "path": "/components/contentSwitcher" },
        { "name": "Размеры", "path": "/components/contentSwitcher/sizes" },
        { "name": "Стили", "path": "/components/contentSwitcher/styles" },
        { "name": "С иконками", "path": "/components/contentSwitcher/withIcons" },
        { "name": "С Badge", "path": "/components/contentSwitcher/withBadge" },
        { "name": "Иконки без текста", "path": "/components/contentSwitcher/iconsOnly" },
        { "name": "Адаптив", "path": "/components/contentSwitcher/adaptive" }
      ]
    },
    {
      "name": "Chips",
      "path": "/components/chips",
      "routes": [
        { "name": "Базовый пример", "path": "/components/chips" },
        { "name": "Размеры", "path": "/components/chips/sizes" },
        { "name": "Стили", "path": "/components/chips/styles" },
        { "name": "Chips с текстом и иконкой закрыть", "path": "/components/chips/chipsClose" },
        { "name": "Chips с иконкой", "path": "/components/chips/withIcon" },
        { "name": "Chips с Badge", "path": "/components/chips/withBadge" },
        { "name": "Chips с текстом и выбором", "path": "/components/chips/select" },
        { "name": "Chips для множественного выбора", "path": "/components/chips/multiSelect" },
        { "name": "Chips с Tooltip", "path": "/components/chips/withTooltip" }
      ]
    },
    {
      "name": "Tag",
      "path": "/components/tag",
      "routes": [
        { "name": "Базовый пример", "path": "/components/tag" },
        { "name": "Стили и размеры", "path": "/components/tag/styles" },
        { "name": "Тултип", "path": "/components/tag/tooltip" },
        { "name": "С иконкой", "path": "/components/tag/withIcon" },
        { "name": "Группа тэгов", "path": "/components/tag/tags" },
        { "name": "С выпадающим меню", "path": "/components/tag/menu" }
      ]
    },
    {
      "name": "Badge",
      "path": "/components/badge",
      "routes": [
        { "name": "Базовый пример", "path": "/components/badge" },
        { "name": "Варианты использования", "path": "/components/badge/badgeVariants" },
        { "name": "Accessibility", "path": "/components/badge/badgeAccessibility" }
      ]
    },
    {
      "name": "BadgeDot",
      "path": "/components/badgeDot",
      "routes": [
        { "name": "Базовый пример", "path": "/components/badgeDot" },
        { "name": "Варианты использования", "path": "/components/badgeDot/variants" }
      ]
    },
    {
      "name": "Pills",
      "path": "/components/pills",
      "routes": [
        { "name": "Базовый пример", "path": "/components/pills" },
        { "name": "С выпадающим меню", "path": "/components/pills/menu" },
        { "name": "Тултип", "path": "/components/pills/tooltip" },
        { "name": "Двойные Pills", "path": "/components/pills/nested" }
      ]
    },
    {
      "name": "Drawer",
      "path": "/components/drawer",
      "routes": [
        { "name": "Базовый пример", "path": "/components/drawer" },
        { "name": "Блокировка контента страницы (Backdrop = True)", "path": "/components/drawer/withBackdrop" },
        { "name": "Без блокировки контента страницы (Backdrop = False)", "path": "/components/drawer/withoutBackdrop" },
        { "name": "С обязательным условием (non-closable Drawer)", "path": "/components/drawer/nonClosable" },
        { "name": "Расположение компонента", "path": "/components/drawer/position" },
        { "name": "Адаптив (mobile)", "path": "/components/drawer/mobile" },
        { "name": "Ширина компонента", "path": "/components/drawer/width" },
        { "name": "Свободное (кастомизированное) наполнение", "path": "/components/drawer/customContent" }
      ]
    },
    {
      "name": "Dropdown Menu",
      "path": "/components/dropdown",
      "routes": [
        { "name": "Базовый пример", "path": "/components/dropdown" },
        {
          "name": "DropMenu. Неконтроллируемое состояние видимости",
          "path": "/components/dropdown/dropMenuUncontrolled"
        },
        { "name": "DropMenu. Контроллируемое состояние видимости", "path": "/components/dropdown/dropMenuControlled" },
        { "name": "DropdownContainer. Контейнер с меню", "path": "/components/dropdown/customDropdownContainer" },
        { "name": "Menu. Размеры", "path": "/components/dropdown/menuDimensions" },
        { "name": "Menu. С иконками", "path": "/components/dropdown/menuWithIcons" },
        { "name": "Menu. С дополнительным текстом и иконками", "path": "/components/dropdown/menuWithAddTextAndIcons" },
        { "name": "Menu. С RadioButton", "path": "/components/dropdown/menuWithRadioButton" },
        { "name": "Menu. С Checkbox", "path": "/components/dropdown/menuWithCheckbox" },
        { "name": "Menu. С CheckboxGroup", "path": "/components/dropdown/menuWithCheckboxGroup" },
        { "name": "Menu. Длинный текст", "path": "/components/dropdown/menuWithTooltip" },
        { "name": "Menu. Категории", "path": "/components/dropdown/menuCategories" },
        { "name": "Menu. Кастомные пункты меню", "path": "/components/dropdown/menuCustomItems" },
        { "name": "Menu. Многострочные пункты", "path": "/components/dropdown/menuMultiLine" },
        { "name": "Menu. Пример с Actions с двумя кнопками", "path": "/components/dropdown/menuActionTwoButtons" },
        { "name": "Menu. Пример с Actions и Search", "path": "/components/dropdown/menuActionSearch" },
        { "name": "Menu. Пример с большим количеством item", "path": "/components/dropdown/menuManyItems" },
        { "name": "Menu. Пример без цикла обхода пунктов", "path": "/components/dropdown/menuLockCycleScroll" },
        { "name": "Menu. Виртуальный скролл", "path": "/components/dropdown/menuVirtualScroll" },
        { "name": "Menu. Многоуровневое меню", "path": "/components/dropdown/menuMultiLevel" },
        { "name": "Menu. Меню c состоянием preselect", "path": "/components/dropdown/menuPreselect" }
      ]
    },
    {
      "name": "ImageViewer",
      "path": "/components/imageViewer",
      "routes": [
        { "name": "Базовый пример", "path": "/components/imageViewer" },
        { "name": "Отображение миниатюр", "path": "/components/imageViewer/imageMiniature" },
        { "name": "Алгоритм отображения", "path": "/components/imageViewer/viewOptions" },
        { "name": "Ошибки при загрузке", "path": "/components/imageViewer/errorOnLoad" },
        { "name": "Клавиатурные команды", "path": "/components/imageViewer/keyboardCommands" }
      ]
    },
    {
      "name": "Table",
      "path": "/components/table",
      "routes": [
        { "name": "Базовый пример", "path": "/components/table" },
        { "name": "Изменение ширины столбцов", "path": "/components/table/width" },
        { "name": "Пример с чекбоксами", "path": "/components/table/checkbox" },
        { "name": "Сортировка", "path": "/components/table/sort" },
        { "name": "Фильтрация", "path": "/components/table/filter" },
        { "name": "Фиксирванные столбцы", "path": "/components/table/sticky" },
        {
          "name": "Пример строк с OverflowMenu и иконками одиночных действий",
          "path": "/components/table/overflowMenu"
        },
        { "name": "Детализация строк", "path": "/components/table/expand" },
        { "name": "Группировка строк", "path": "/components/table/group" },
        {
          "name": "Виртуальный скролл для строк с фиксированной высотой",
          "path": "/components/table/fixedVirtualScroll"
        },
        {
          "name": "Виртуальный скролл для строк с динамической высотой",
          "path": "/components/table/dynamicVirtualScroll"
        },
        {
          "name": "Drag&Drop столбцов",
          "path": "/components/table/columnDragDrop"
        },
        {
          "name": "Drag&Drop строк",
          "path": "/components/table/rowDragDrop"
        },
        { "name": "Стилизация компонента", "path": "/components/table/style" },
        { "name": "Состояния и статусы строк", "path": "/components/table/rowState" },
        { "name": "Зебра (окрашивание строк через одну)", "path": "/components/table/zebra" },
        { "name": "Многострочность", "path": "/components/table/multiline" },
        { "name": "Дополнительный текст в заголовке", "path": "/components/table/extraText" },
        { "name": "Использование render-колбеков", "path": "/components/table/renderCallback" },
        { "name": "Управление позицией скролла через ref-атрибут", "path": "/components/table/scrollPositionByRef" },
        { "name": "Подгрузка данных при скролле", "path": "/components/table/loadOnScroll" },
        { "name": "Подгрузка данных при скролле со спиннером", "path": "/components/table/loadOnScrollSpinner" },
        { "name": "Подгрузка данных при скролле со скелетоном", "path": "/components/table/loadOnScrollSkeleton" },
        { "name": "Базовый HTML table", "path": "/components/table/baseHTML" },
        { "name": "Базовый HTML table с фиксированными столбцами", "path": "/components/table/baseHTMLStickyShadow" },
        { "name": "Базовый HTML table с OverflowMenu", "path": "/components/table/baseHTMLOverflowMenu" },
        { "name": "Базовый HTML table с multi-level header", "path": "/components/table/multiLevelHeader" }
      ]
    },
    {
      "name": "List",
      "path": "/components/list",
      "routes": [
        { "name": "Базовый пример", "path": "/components/list" },
        { "name": "OrderedList. Виды и размеры.", "path": "/components/list/orderedList" },
        { "name": "UnorderedList. Виды и размеры.", "path": "/components/list/unorderedList" },
        { "name": "Многострочность и регулировка ширины списка", "path": "/components/list/multiline" },
        { "name": "Вложенные списки", "path": "/components/list/nested" },
        { "name": "Кастомный цвет маркера", "path": "/components/list/markerColor" },
        { "name": "Кастомизация маркеров", "path": "/components/list/customMarker" }
      ]
    },
    {
      "name": "Notification",
      "path": "/components/notification",
      "routes": [
        { "name": "Базовый пример", "path": "/components/notification" },
        { "name": "Стили", "path": "/components/notification/styles" },
        { "name": "Состояния", "path": "/components/notification/states" }
      ]
    },
    {
      "name": "Toast",
      "path": "/components/toast",
      "routes": [
        { "name": "Базовый пример", "path": "/components/toast" },
        { "name": "Расположение уведомлений", "path": "/components/toast/position" },
        { "name": "Опция Countdown", "path": "/components/toast/withProgressBar" },
        { "name": "Задержка при наведении", "path": "/components/toast/withProgressBarStopOnHover" },
        { "name": "Line Notification", "path": "/components/toast/lineNotification" }
      ]
    },
    {
      "name": "OverflowMenu",
      "path": "/components/overflowMenu",
      "routes": [
        { "name": "Базовый пример", "path": "/components/overflowMenu" },
        { "name": "Размеры и ориентация", "path": "/components/overflowMenu/styles" },
        { "name": "Пример многоуровневого меню", "path": "/components/overflowMenu/multiLevel" }
      ]
    },
    {
      "name": "Modal",
      "path": "/components/modal",
      "routes": [
        { "name": "Базовый пример", "path": "/components/modal" },
        { "name": "Размеры", "path": "/components/modal/sizes" },
        { "name": "Наполнение", "path": "/components/modal/variants" },
        { "name": "Скролл", "path": "/components/modal/scroll" },
        { "name": "Кастомизация подложки модального окна", "path": "/components/modal/customOverlay" },
        { "name": "Иконка закрытия", "path": "/components/modal/closeIcon" },
        { "name": "Статусные иконки", "path": "/components/modal/statusIcons" }
      ]
    },
    {
      "name": "Hint",
      "path": "/components/hint",
      "routes": [
        { "name": "Базовый пример", "path": "/components/hint" },
        { "name": "Размеры", "path": "/components/hint/sizes" },
        { "name": "Сценарии появления", "path": "/components/hint/scenario" },
        { "name": "Позиционирование", "path": "/components/hint/position" },
        { "name": "Наполнение", "path": "/components/hint/variants" },
        { "name": "ClassName", "path": "/components/hint/className" },
        { "name": "Стилизация внешнего контейнера", "path": "/components/hint/anchorCssMixin" }
      ]
    },
    {
      "name": "Tooltip",
      "path": "/components/tooltip",
      "routes": [
        { "name": "Базовый пример", "path": "/components/tooltip" },
        { "name": "Размеры", "path": "/components/tooltip/sizes" },
        { "name": "Сценарии появления", "path": "/components/tooltip/scenario" },
        { "name": "Позиционирование", "path": "/components/tooltip/position" },
        { "name": "Кастомное наполнение", "path": "/components/tooltip/variants" },
        { "name": "Пример с получением ref тултипа", "path": "/components/tooltip/ref" },
        { "name": "Базовый пример с MenuButton", "path": "/components/tooltip/withMenuButton" },
        { "name": "TooltipHoc. Базовый пример", "path": "/components/tooltip/hocBase" },
        { "name": "TooltipHoc. Пример использования с классовым компонентом", "path": "/components/tooltip/hocClass" },
        {
          "name": "TooltipHoc. Пример использования с функциональным компонентом",
          "path": "/components/tooltip/hocFC"
        },
        { "name": "TooltipHoc. Прокидывание ref на результат вызова TooltipHoc", "path": "/components/tooltip/hocRef" },
        { "name": "TooltipHoc. Утилита refSetter для мерджа рефов.", "path": "/components/tooltip/hocRefSetter" }
      ]
    },
    {
      "name": "Flex",
      "path": "/components/flex",
      "routes": [{ "name": "Базовый пример", "path": "/components/flex" }]
    },
    {
      "name": "GroupActionsPane",
      "path": "/components/groupActionsPane",
      "routes": [{ "name": "Базовый пример", "path": "/components/groupActionsPane" }]
    },
    {
      "name": "PaginationTwo",
      "path": "/components/paginationTwo",
      "routes": [
        { "name": "Базовый пример", "path": "/components/paginationTwo" },
        { "name": "Количество страниц", "path": "/components/paginationTwo/pages" },
        { "name": "Ввод номера страницы вручную", "path": "/components/paginationTwo/withInput" },
        { "name": "Состояния", "path": "/components/paginationTwo/state" },
        { "name": "Количество записей", "path": "/components/paginationTwo/entries" },
        { "name": "Мобильная версия", "path": "/components/paginationTwo/mobile" }
      ]
    },
    {
      "name": "PaginationOne",
      "path": "/components/paginationOne",
      "routes": [
        { "name": "Базовый пример", "path": "/components/paginationOne" },
        { "name": "Размеры", "path": "/components/paginationOne/sizes" },
        { "name": "Типы", "path": "/components/paginationOne/types" },
        { "name": "Состояния", "path": "/components/paginationOne/states" },
        { "name": "Опция ввода номера страницы через Input", "path": "/components/paginationOne/withInput" }
      ]
    },
    {
      "name": "ProgressPage",
      "path": "/components/progressPage",
      "routes": [
        { "name": "Базовый пример", "path": "/components/progressPage" },
        { "name": "Стили", "path": "/components/progressPage/styles" },
        { "name": "Анимация", "path": "/components/progressPage/animation" }
      ]
    },
    {
      "name": "ProgressHeader",
      "path": "/components/progressHeader",
      "routes": [
        { "name": "Базовый пример", "path": "/components/progressHeader" },
        { "name": "Стили", "path": "/components/progressHeader/styles" },
        { "name": "Анимация", "path": "/components/progressHeader/animation" }
      ]
    },
    {
      "name": "ProgressStepper",
      "path": "/components/progressStepper",
      "routes": [
        { "name": "Базовый пример", "path": "/components/progressStepper" },
        { "name": "Сценарий прогресса", "path": "/components/progressStepper/scenario" },
        { "name": "Адаптив (mobile)", "path": "/components/progressStepper/mobile" },
        { "name": "Пример настройки названия шага", "path": "/components/progressStepper/stepsNaming" },
        {
          "name": "Примеры настройки подписи о следующем шаге",
          "path": "/components/progressStepper/descriptionNextSteps"
        }
      ]
    },
    {
      "name": "GlobalSearch",
      "path": "/components/globalSearch",
      "routes": [
        { "name": "Базовый пример", "path": "/components/globalSearch" },
        { "name": "Размеры", "path": "/components/globalSearch/sizes" },
        { "name": "Варианты", "path": "/components/globalSearch/variants" }
      ]
    },
    {
      "name": "TabMenu",
      "path": "/components/tabMenu",
      "routes": [
        { "name": "TabMenuHorizontal. Базовый пример", "path": "/components/tabMenu" },
        { "name": "TabMenuHorizontal. Размеры", "path": "/components/tabMenu/size" },
        { "name": "TabMenuHorizontal. С Overflow Menu", "path": "/components/tabMenu/withOverflowMenu" },
        { "name": "TabMenuHorizontal. Опции", "path": "/components/tabMenu/options" },
        { "name": "TabMenuHorizontal. С добавлением и удалением вкладок", "path": "/components/tabMenu/addTab" },
        { "name": "CardTabMenu. Базовый пример", "path": "/components/tabMenu/cardTabMenu" },
        { "name": "CardTabMenu. С отступами", "path": "/components/tabMenu/withPadding" },
        { "name": "CardTabMenu. С добавлением и удалением вкладок", "path": "/components/tabMenu/addCardTab" },
        { "name": "CardTabMenu. Без обводки", "path": "/components/tabMenu/cardTabMenuWithoutBorder" },
        { "name": "TabMenuVertical. Базовый пример", "path": "/components/tabMenu/tabMenuVertical" },
        { "name": "TabMenuVertical. Размеры", "path": "/components/tabMenu/sizeVerticalTabs" },
        { "name": "TabMenuVertical. Опции", "path": "/components/tabMenu/optionsVerticalTabs" },
        { "name": "TabMenuVertical. Добавление и удаление вкладок", "path": "/components/tabMenu/addTabVertical" },
        { "name": "TabMenuIcon. Базовый пример", "path": "/components/tabMenu/tabMenuIcon" },
        { "name": "HorizontalTabs. Базовый пример", "path": "/components/tabMenu/horizontalTabs" },
        { "name": "FilterTabs. Базовый пример", "path": "/components/tabMenu/filterTabs" },
        { "name": "FilterTabs. Размеры", "path": "/components/tabMenu/filterTabsSize" },
        { "name": "FilterTabs. Мобильная версия", "path": "/components/tabMenu/filterTabsMobile" }
      ]
    },
    {
      "name": "StatusIndicator",
      "path": "/components/statusIndicator",
      "routes": [
        { "name": "Базовый пример", "path": "/components/statusIndicator" },
        { "name": "Размеры", "path": "/components/statusIndicator/sizes" },
        { "name": "Варианты", "path": "/components/statusIndicator/variants" },
        { "name": "Состояния", "path": "/components/statusIndicator/states" }
      ]
    },
    {
      "name": "Stepper",
      "path": "/components/stepper",
      "routes": [
        { "name": "Базовый пример", "path": "/components/stepper" },
        { "name": "Состояния", "path": "/components/stepper/state" },
        { "name": "Варианты отображения строк", "path": "/components/stepper/variants" },
        { "name": "Опции", "path": "/components/stepper/options" },
        { "name": "Кастомный StepContent", "path": "/components/stepper/custom" },
        { "name": "Вертикальный Stepper", "path": "/components/stepper/vertical" },
        { "name": "Адаптив", "path": "/components/stepper/adaptive" },
        { "name": "Мобильная версия", "path": "/components/stepper/mobile" }
      ]
    },
    {
      "name": "SegmentedControl",
      "path": "/components/segmentedControl",
      "routes": [
        { "name": "Базовый пример", "path": "/components/segmentedControl" },
        { "name": "Стили", "path": "/components/segmentedControl/styles" },
        { "name": "Размеры", "path": "/components/segmentedControl/sizes" },
        { "name": "Варианты", "path": "/components/segmentedControl/variants" },
        { "name": "Состояния", "path": "/components/segmentedControl/states" },
        { "name": "Режим radio button", "path": "/components/segmentedControl/radioButtonMode" },
        { "name": "Режим checkbox", "path": "/components/segmentedControl/checkBoxMode" }
      ]
    },
    {
      "name": "Spinner",
      "path": "/components/spinner",
      "routes": [
        { "name": "Базовый пример", "path": "/components/spinner" },
        { "name": "Размеры", "path": "/components/spinner/sizes" },
        { "name": "Варианты", "path": "/components/spinner/variants" },
        { "name": "В составе других компонентов", "path": "/components/spinner/withOtherComponents" }
      ]
    },
    {
      "name": "Slider",
      "path": "/components/slider",
      "routes": [
        { "name": "Базовый пример", "path": "/components/slider" },
        { "name": "Размеры", "path": "/components/slider/sizes" },
        { "name": "Состояния", "path": "/components/slider/state" },
        { "name": "C настройками minValue, maxValue", "path": "/components/slider/options" },
        { "name": "C отметками и кастомизированными подписями к ним", "path": "/components/slider/custom" },
        { "name": "Range. Базовый пример", "path": "/components/slider/range" },
        { "name": "Range. Размеры", "path": "/components/slider/rangeSizes" },
        { "name": "Range. Состояния", "path": "/components/slider/rangeState" },
        { "name": "Range. C настройками minValue, maxValue", "path": "/components/slider/rangeOptions" }
      ]
    },
    {
      "name": "Skeleton",
      "path": "/components/skeleton",
      "routes": [{ "name": "Базовый пример", "path": "/components/skeleton" }]
    },
    {
      "name": "Tree",
      "path": "/components/tree",
      "routes": [
        { "name": "Базовый пример", "path": "/components/tree" },
        { "name": "Размеры", "path": "/components/tree/sizes" },
        { "name": "Варианты", "path": "/components/tree/variants" },
        { "name": "Произвольный контент", "path": "/components/tree/custom" },
        { "name": "Неконтролируемое дерево", "path": "/components/tree/uncontrolled" },
        { "name": "Со счётчиком", "path": "/components/tree/withControlCheckCount" },
        {
          "name": "Обработка событий onExpandChange и onCheckedChange",
          "path": "/components/tree/withOnChangeHandler"
        },
        { "name": "Мобильная версия", "path": "/components/tree/mobile" }
      ]
    },
    {
      "name": "T",
      "path": "/components/t",
      "routes": [
        { "name": "Базовый пример", "path": "/components/t" },
        { "name": "Варианты использования", "path": "/components/t/variants" },
        { "name": "Список стилей", "path": "/components/t/stylesList" }
      ]
    },
    {
      "name": "ScrollContainer",
      "path": "/components/scrollContainer",
      "routes": [
        { "name": "Базовый пример", "path": "/components/scrollContainer" },
        { "name": "Состояния", "path": "/components/scrollContainer/state" }
      ]
    },
    {
      "name": "DateInput",
      "path": "/components/dateInput",
      "routes": [
        { "name": "Базовый пример", "path": "/components/dateInput" },
        { "name": "Размеры", "path": "/components/dateInput/sizes" },
        { "name": "Состояния", "path": "/components/dateInput/state" },
        { "name": "Статусы", "path": "/components/dateInput/status" },
        { "name": "Type \"date-range\"", "path": "/components/dateInput/range" },
        { "name": "Варианты отображения дат", "path": "/components/dateInput/variants" },
        { "name": "С альтернативной иконкой", "path": "/components/dateInput/custom" },
        { "name": "Выделение определённых дат", "path": "/components/dateInput/specialDates" },
        { "name": "С кнопкой \"Сегодня\"", "path": "/components/dateInput/withButton" },
        { "name": "DateField. Базовый пример", "path": "/components/dateInput/dateField" },
        { "name": "DateField. Состояния", "path": "/components/dateInput/dateFieldState" }
      ]
    },
    {
      "name": "Select",
      "path": "/components/select",
      "routes": [
        { "name": "Базовый пример", "path": "/components/select" },
        { "name": "Размеры", "path": "/components/select/sizes" },
        { "name": "Состояния", "path": "/components/select/state" },
        { "name": "Статусы", "path": "/components/select/status" },
        {
          "name": "Кастомные опции с кастомной фильтрацией",
          "path": "/components/select/customOptionsWithCustomFilter"
        },
        { "name": "Кастомные опции через renderProps", "path": "/components/select/customOptionsByRenderProps" },
        { "name": "Подгрузка данных при scroll", "path": "/components/select/progressiveRenderOptionsScroll" },
        { "name": "Скрыть Tooltip при переполнении Title", "path": "/components/select/forceHideOverflowTooltip" },
        { "name": "Кастомное отображение значения", "path": "/components/select/customValues" },
        {
          "name": "Кастомное отображение значения с множетвенным выбором",
          "path": "/components/select/multiCustomValues"
        },
        { "name": "Нижняя панель с кнопкой \"Добавить\"", "path": "/components/select/panelWithAddButton" },
        { "name": "Использование групп", "path": "/components/select/groupOfOptions" },
        { "name": "Ассинхронный поиск", "path": "/components/select/asyncSearch" },
        { "name": "Неконтролируемый сабмит", "path": "/components/select/uncontrolledSubmitSearch" },
        { "name": "Multiple с кнопкой \"Применить\"", "path": "/components/select/multiSelectApplyButton" },
        { "name": "Multiple с кнопкой \"Выбрать все\"", "path": "/components/select/multiSelectChooseAll" },
        {
          "name": "Multiple с увеличенной по умолчанию высотой",
          "path": "/components/select/multiSelectExpandedHeight"
        },
        { "name": "Multiple с кастомными опциями", "path": "/components/select/multiCustomOptionsByRenderChip" },
        {
          "name": "Multiple с кастомным удалением чипса",
          "path": "/components/select/multiCustomDeleteChip"
        },
        { "name": "Multiple с обработчиком события onChange", "path": "/components/select/multiSelectOnChange" },
        {
          "name": "Multiple с поднятием выбранных опций вверх списка",
          "path": "/components/select/multiSelectWithSelectedOnTop"
        },
        {
          "name": "Multiple с опцией очистки введенного значения после выбора",
          "path": "/components/select/searchWithClearInputAfterSelect"
        },
        { "name": "Внешняя фильтрация", "path": "/components/select/externalFilter" },
        { "name": "VirtualScroll", "path": "/components/select/virtualScroll" },
        { "name": "SelectField. Базовый пример", "path": "/components/select/selectField" }
      ]
    },
    {
      "name": "Anchor",
      "path": "/components/anchor",
      "routes": [
        { "name": "Базовый пример", "path": "/components/anchor" },
        { "name": "Размеры", "path": "/components/anchor/sizes" },
        { "name": "Tree", "path": "/components/anchor/tree" },
        { "name": "Состояния", "path": "/components/anchor/state" }
      ]
    },
    {
      "name": "DateTimeField",
      "path": "/components/dateTimeField",
      "routes": [
        { "name": "Базовый пример", "path": "/components/dateTimeField" },
        { "name": "Размеры", "path": "/components/dateTimeField/dimension" },
        { "name": "Дополнительный текст", "path": "/components/dateTimeField/extraText" },
        { "name": "С подписью в одну линию", "path": "/components/dateTimeField/displayInline" },
        { "name": "Состояние/статус", "path": "/components/dateTimeField/status" }
      ]
    },
    {
      "name": "Divider",
      "path": "/components/divider",
      "routes": [
        { "name": "Базовый пример", "path": "/components/divider" },
        { "name": "Тип (ориентация)", "path": "/components/divider/type" },
        { "name": "Стиль", "path": "/components/divider/style" },
        { "name": "Толщина линии", "path": "/components/divider/thikness" },
        { "name": "Длина", "path": "/components/divider/length" }
      ]
    },
    {
      "name": "Calendar",
      "path": "/components/calendar",
      "routes": [
        { "name": "Базовый пример", "path": "/components/calendar" },
        { "name": "Range", "path": "/components/calendar/range" },
        { "name": "Ограничение максимальной даты", "path": "/components/calendar/maxDate" },
        { "name": "Недоступные для выбора даты", "path": "/components/calendar/filterDate" },
        { "name": "Callback", "path": "/components/calendar/callback" },
        { "name": "Переключение экранов выбора дат", "path": "/components/calendar/activeViewDate" },
        {
          "name": "Пример с открытием экрана выбора месяца после выбора года",
          "path": "/components/calendar/viewDateAfterChoose"
        },
        {
          "name": "Пример с выбором только месяца/года",
          "path": "/components/calendar/viewDateMonthsYears"
        },
        {
          "name": "Выделение определённых дат",
          "path": "/components/calendar/specialDates"
        }
      ]
    },
    {
      "name": "EditMode",
      "path": "/components/editmode",
      "routes": [
        { "name": "Базовый пример", "path": "/components/editmode" },
        { "name": "Размеры", "path": "/components/editmode/dimensions" },
        { "name": "Статусы/состояния", "path": "/components/editmode/status" },
        { "name": "Многострочный компонент", "path": "/components/editmode/multiline" },
        { "name": "Невозможность копирования", "path": "/components/editmode/disablecopying" },
        { "name": "Тултип", "path": "/components/editmode/tooltip" },
        { "name": "Дополнительный текст", "path": "/components/editmode/extratext" }
      ]
    },
    {
      "name": "PhoneNumberInput",
      "path": "/components/phoneNumberInput",
      "routes": [
        { "name": "Базовый пример", "path": "/components/phoneNumberInput" },
        { "name": "Размеры", "path": "/components/phoneNumberInput/sizes" },
        { "name": "Состояния", "path": "/components/phoneNumberInput/state" },
        { "name": "Статусы", "path": "/components/phoneNumberInput/status" },
        { "name": "С фильтрацией списка", "path": "/components/phoneNumberInput/withFilter" },
        { "name": "С заданной страной по умолчанию", "path": "/components/phoneNumberInput/selectedCountry" },
        { "name": "С placeholder", "path": "/components/phoneNumberInput/withPlaceholder" },
        { "name": "PhoneNumberInputField", "path": "/components/phoneNumberInput/phoneNumberInputField" }
      ]
    },
    {
      "name": "NumberInput",
      "path": "/components/numberInput",
      "routes": [
        { "name": "Базовый пример", "path": "/components/numberInput" },
        { "name": "Размеры", "path": "/components/numberInput/sizes" },
        { "name": "Состояния", "path": "/components/numberInput/state" },
        { "name": "Статусы", "path": "/components/numberInput/status" },
        { "name": "С minValue, maxValue", "path": "/components/numberInput/minMaxValue" },
        { "name": "С изменением настроек suffix, precision, thousand", "path": "/components/numberInput/custom" },
        { "name": "Скрытые пробелы", "path": "/components/numberInput/spaces" },
        { "name": "Контролируемый инпут", "path": "/components/numberInput/controlledInput" },
        { "name": "NumberInputField", "path": "/components/numberInput/numberInputField" }
      ]
    },
    {
      "name": "FileInput",
      "path": "/components/fileinput",
      "routes": [
        { "name": "Базовый пример", "path": "/components/fileinput" },
        { "name": "Размеры", "path": "/components/fileinput/dimensions" },
        { "name": "Состояния/статусы", "path": "/components/fileinput/state" },
        { "name": "Дополнительный текст", "path": "/components/fileinput/extratext" },
        { "name": "Статусы загрузки файлов", "path": "/components/fileinput/filestatus" },
        { "name": "Катомизация", "path": "/components/fileinput/customizing" },
        { "name": "Катомизация типов файлов", "path": "/components/fileinput/customizingFileType" }
      ]
    },
    {
      "name": "InputEx",
      "path": "/components/inputEx",
      "routes": [
        { "name": "Базовый пример", "path": "/components/inputEx" },
        { "name": "Размеры", "path": "/components/inputEx/sizes" },
        { "name": "Состояния", "path": "/components/inputEx/state" },
        { "name": "Статусы", "path": "/components/inputEx/status" },
        { "name": "C выбором префикса и суффикса", "path": "/components/inputEx/prefixSuffixSelect" },
        { "name": "Custom", "path": "/components/inputEx/custom" },
        { "name": "InputExField. Базовый пример", "path": "/components/inputEx/inputExField" }
      ]
    },
    {
      "name": "CurrencyInput",
      "path": "/components/currencyInput",
      "routes": [
        { "name": "Базовый пример", "path": "/components/currencyInput" },
        { "name": "С префиксом", "path": "/components/currencyInput/withPrefix" },
        { "name": "С minValue, maxValue", "path": "/components/currencyInput/minMaxvalue" },
        { "name": "СurrencyInputField. Базовый пример", "path": "/components/currencyInput/currencyInputField" }
      ]
    },
    {
      "name": "MultiInput",
      "path": "/components/multiInput",
      "routes": [
        { "name": "Базовый пример", "path": "/components/multiInput" },
        { "name": "Размеры", "path": "/components/multiInput/size" },
        { "name": "Состояния", "path": "/components/multiInput/state" },
        { "name": "Статусы", "path": "/components/multiInput/status" },
        { "name": "С начальными опциями", "path": "/components/multiInput/withOptions" }
      ]
    },
    {
      "name": "SliderInput",
      "path": "/components/sliderInput",
      "routes": [
        { "name": "Базовый пример", "path": "/components/sliderInput" },
        { "name": "Размеры", "path": "/components/sliderInput/sizes" },
        { "name": "Состояния", "path": "/components/sliderInput/states" },
        { "name": "Варианты использования", "path": "/components/sliderInput/variants" },
        { "name": "Кастомизация", "path": "/components/sliderInput/custom" },
        { "name": "Контроллируемый инпут", "path": "/components/sliderInput/controlled" }
      ]
    },
    {
      "name": "TextArea",
      "path": "/components/textArea",
      "routes": [
        { "name": "Базовый пример", "path": "/components/textArea" },
        { "name": "Размеры", "path": "/components/textArea/sizes" },
        { "name": "Состояния", "path": "/components/textArea/states" },
        { "name": "Статусы", "path": "/components/textArea/statuses" },
        { "name": "Варианты использования", "path": "/components/textArea/variants" }
      ]
    },
    {
      "name": "SliderRangeInput",
      "path": "/components/sliderRangeInput",
      "routes": [
        { "name": "Базовый пример", "path": "/components/sliderRangeInput" },
        { "name": "Размеры", "path": "/components/sliderRangeInput/sizes" },
        { "name": "Состояния", "path": "/components/sliderRangeInput/states" },
        { "name": "Варианты использования", "path": "/components/sliderRangeInput/variants" },
        { "name": "Кастомизация", "path": "/components/sliderRangeInput/custom" },
        { "name": "Контроллируемый инпут", "path": "/components/sliderRangeInput/controlled" }
      ]
    }
  ]
}
